dash_financial_charts/DashFinancialCharts.py
dash_financial_charts/__init__.py
dash_financial_charts/_imports_.py
dash_financial_charts/dash_financial_charts.min.js
dash_financial_charts/dash_financial_charts.min.js.map
dash_financial_charts/metadata.json
dash_financial_charts/package-info.json
dash_financial_charts-0.0.2.dist-info/LICENSE
dash_financial_charts-0.0.2.dist-info/METADATA
dash_financial_charts-0.0.2.dist-info/WHEEL
dash_financial_charts-0.0.2.dist-info/top_level.txt
dash_financial_charts-0.0.2.dist-info/RECORD
