Metadata-Version: 2.1
Name: dash_financial_charts
Version: 0.0.2
Summary: Wrapper of React Financial Charts for Dash
Author: José Luiz Ferreira <jlfsjunior@gmail.com>
License: MIT
Platform: UNKNOWN
Classifier: Framework :: Dash
License-File: LICENSE
